fbn/__init__.py
fbn/__main__.py
fbn/cli.py
fbn/constants.py
fbn/exceptions.py
fbn/fb.py
fbn-0.1.2.dist-info/LICENSE
fbn-0.1.2.dist-info/METADATA
fbn-0.1.2.dist-info/WHEEL
fbn-0.1.2.dist-info/entry_points.txt
fbn-0.1.2.dist-info/top_level.txt
fbn-0.1.2.dist-info/RECORD
