Metadata-Version: 2.1
Name: fbn
Version: 0.1.2
Summary: Tool to monitor fb groups and notify
Home-page: https://github.com/viseshrp/fbn
Author: Visesh Prasad
Author-email: visesh@live.com
Maintainer: Visesh Prasad
Maintainer-email: visesh@live.com
License: MIT license
Project-URL: Documentation, https://github.com/viseshrp/fbn
Project-URL: Changelog, https://github.com/viseshrp/fbn/blob/main/CHANGELOG.md
Project-URL: Bug Tracker, https://github.com/viseshrp/fbn/issues
Project-URL: Source Code, https://github.com/viseshrp/fbn
Keywords: fb fbn facebook group notify monitor
Classifier: Development Status :: 4 - Beta
Classifier: Intended Audience :: Developers
Classifier: License :: OSI Approved :: MIT License
Classifier: Operating System :: OS Independent
Classifier: Programming Language :: Python :: 3.7
Classifier: Programming Language :: Python :: 3.8
Classifier: Programming Language :: Python :: 3.9
Classifier: Programming Language :: Python :: 3.10
Classifier: Programming Language :: Python :: 3.11
Classifier: Topic :: Software Development :: Libraries :: Python Modules
Requires-Python: >=3.7
License-File: LICENSE
Requires-Dist: click (>=8.1.3)
Requires-Dist: facebook-scraper (>=0.2.59)
Requires-Dist: tenacity (>=8.1.0)
Requires-Dist: schedule (>=1.1.0)
Requires-Dist: apprise (>=1.2.1)
